sdfest/__init__.py
sdfest/utils.py
sdfest/differentiable_renderer/__init__.py
sdfest/differentiable_renderer/sdf_renderer.py
sdfest/differentiable_renderer/simple_renderer.py
sdfest/differentiable_renderer/csrc/sdf_renderer.cpp
sdfest/differentiable_renderer/csrc/sdf_renderer_cuda.cu
sdfest/differentiable_renderer/scripts/__init__.py
sdfest/differentiable_renderer/scripts/experiments.py
sdfest/estimation/__init__.py
sdfest/estimation/losses.py
sdfest/estimation/metrics.py
sdfest/estimation/simple_setup.py
sdfest/estimation/synthetic.py
sdfest/estimation/configs/ablation_study.yaml
sdfest/estimation/configs/default.yaml
sdfest/estimation/configs/real275.yaml
sdfest/estimation/configs/real275_evaluation.yaml
sdfest/estimation/configs/redwood.yaml
sdfest/estimation/configs/redwood_evaluation.yaml
sdfest/estimation/configs/rendering_evaluation.yaml
sdfest/estimation/configs/rgbd_objects_uw.yaml
sdfest/estimation/configs/ros.yaml
sdfest/estimation/configs/runtime_analysis.yaml
sdfest/estimation/configs/models/bottle.yaml
sdfest/estimation/configs/models/bowl.yaml
sdfest/estimation/configs/models/camera.yaml
sdfest/estimation/configs/models/can.yaml
sdfest/estimation/configs/models/laptop.yaml
sdfest/estimation/configs/models/mug.yaml
sdfest/estimation/configs/models/mug_discretized_2.yaml
sdfest/estimation/configs/models/mug_quaternion.yaml
sdfest/estimation/configs/rendering_evaluation_normalized_size/rendering_evaluation_normalized_bottle.yaml
sdfest/estimation/configs/rendering_evaluation_normalized_size/rendering_evaluation_normalized_bowl.yaml
sdfest/estimation/configs/rendering_evaluation_normalized_size/rendering_evaluation_normalized_mug.yaml
sdfest/estimation/scripts/__init__.py
sdfest/estimation/scripts/play_log.py
sdfest/estimation/scripts/real_data.py
sdfest/estimation/scripts/rendering_evaluation.py
sdfest/initialization/__init__.py
sdfest/initialization/pointnet.py
sdfest/initialization/pointset_utils.py
sdfest/initialization/quaternion_utils.py
sdfest-0.1.1.dist-info/LICENSE
sdfest-0.1.1.dist-info/METADATA
sdfest-0.1.1.dist-info/WHEEL
sdfest-0.1.1.dist-info/top_level.txt
sdfest-0.1.1.dist-info/RECORD
